_tgcrypto.cpython-312-darwin.so
tgcrypto2-1.3.4.dist-info/RECORD
tgcrypto2-1.3.4.dist-info/WHEEL
tgcrypto2-1.3.4.dist-info/top_level.txt
tgcrypto2-1.3.4.dist-info/METADATA
tgcrypto2-1.3.4.dist-info/licenses/COPYING.lesser
tgcrypto2-1.3.4.dist-info/licenses/NOTICE
tgcrypto2-1.3.4.dist-info/licenses/COPYING
tgcrypto/__init__.py
