Metadata-Version: 2.4
Name: TgCrypto2
Version: 1.3.4
Summary: Fast and Portable Cryptography Extension Library for Pyrogram
Author-email: Dan <dan@pyrogram.org>
License-Expression: LGPL-3.0-or-later
Project-URL: Homepage, https://github.com/pyrogram
Project-URL: Download, https://github.com/pyrogram/tgcrypto/releases/latest
Project-URL: Tracker, https://github.com/pyrogram/tgcrypto/issues
Project-URL: Community, https://t.me/pyrogram
Project-URL: Source, https://github.com/pyrogram/tgcrypto
Project-URL: Documentation, https://docs.pyrogram.org
Keywords: pyrogram,telegram,crypto,cryptography,encryption,mtproto,extension,library,aes
Classifier: Development Status :: 5 - Production/Stable
Classifier: Intended Audience :: Developers
Classifier: Operating System :: OS Independent
Classifier: Programming Language :: C
Classifier: Programming Language :: Python
Classifier: Programming Language :: Python :: 3
Classifier: Programming Language :: Python :: 3.7
Classifier: Programming Language :: Python :: 3.8
Classifier: Programming Language :: Python :: 3.9
Classifier: Programming Language :: Python :: 3.10
Classifier: Programming Language :: Python :: 3.11
Classifier: Programming Language :: Python :: 3.12
Classifier: Programming Language :: Python :: 3.13
Classifier: Programming Language :: Python :: Implementation
Classifier: Programming Language :: Python :: Implementation :: CPython
Classifier: Programming Language :: Python :: Implementation :: PyPy
Classifier: Topic :: Security
Classifier: Topic :: Security :: Cryptography
Classifier: Topic :: Internet
Classifier: Topic :: Communications
Classifier: Topic :: Communications :: Chat
Classifier: Topic :: Software Development :: Libraries
Classifier: Topic :: Software Development :: Libraries :: Python Modules
Requires-Python: >=3.7
License-File: COPYING
License-File: COPYING.lesser
License-File: NOTICE
Dynamic: license-file
